calibraxis.py
calibraxis-0.2.0.dist-info/DESCRIPTION.rst
calibraxis-0.2.0.dist-info/METADATA
calibraxis-0.2.0.dist-info/RECORD
calibraxis-0.2.0.dist-info/WHEEL
calibraxis-0.2.0.dist-info/metadata.json
calibraxis-0.2.0.dist-info/top_level.txt
