Metadata-Version: 2.0
Name: calibraxis
Version: 0.2.0
Summary: Autocalibration method for accelerometers, implemented in Python.
Home-page: https://github.com/hbldh/calibraxis
Author: Henrik Blidh
Author-email: henrik.blidh@nedobmkull.com
License: MIT
Keywords: Calibration,Accelerometers
Platform: UNKNOWN
Classifier: Development Status :: 4 - Beta
Classifier: Operating System :: OS Independent
Classifier: Intended Audience :: Science/Research
Classifier: Intended Audience :: Developers
Classifier: License :: OSI Approved :: MIT License
Classifier: Topic :: Software Development
Classifier: Topic :: Scientific/Engineering
Classifier: Programming Language :: Python :: 2
Classifier: Programming Language :: Python :: 2.6
Classifier: Programming Language :: Python :: 2.7
Classifier: Programming Language :: Python :: 3
Classifier: Programming Language :: Python :: 3.3
Classifier: Programming Language :: Python :: 3.4
Classifier: Programming Language :: Python :: 3.5
Requires-Dist: numpy (>=1.9.0)
Requires-Dist: six (>=1.9.0)
